odoo/addons/shopinvader_product_brand/README.rst
odoo/addons/shopinvader_product_brand/__init__.py
odoo/addons/shopinvader_product_brand/__manifest__.py
odoo/addons/shopinvader_product_brand/i18n/shopinvader_product_brand.pot
odoo/addons/shopinvader_product_brand/models/__init__.py
odoo/addons/shopinvader_product_brand/models/product_brand.py
odoo/addons/shopinvader_product_brand/readme/CONTRIBUTORS.rst
odoo/addons/shopinvader_product_brand/readme/DESCRIPTION.rst
odoo/addons/shopinvader_product_brand/schemas/__init__.py
odoo/addons/shopinvader_product_brand/schemas/brand.py
odoo/addons/shopinvader_product_brand/schemas/product.py
odoo/addons/shopinvader_product_brand/static/description/index.html
odoo/addons/shopinvader_product_brand/tests/__init__.py
odoo/addons/shopinvader_product_brand/tests/test_product_product.py
odoo/addons/shopinvader_product_brand/views/product_brand_view.xml
odoo_addon_shopinvader_product_brand-16.0.1.0.1.dist-info/METADATA
odoo_addon_shopinvader_product_brand-16.0.1.0.1.dist-info/WHEEL
odoo_addon_shopinvader_product_brand-16.0.1.0.1.dist-info/top_level.txt
odoo_addon_shopinvader_product_brand-16.0.1.0.1.dist-info/RECORD
