Metadata-Version: 2.1
Name: odoo-addon-shopinvader-product-brand
Version: 16.0.1.0.1
Summary: Shopinvader product Brand
Home-page: https://github.com/shopinvader/odoo-shopinvader
Author: Akretion
License: AGPL-3
Platform: UNKNOWN
Classifier: Programming Language :: Python
Classifier: Framework :: Odoo
Classifier: Framework :: Odoo :: 16.0
Classifier: License :: OSI Approved :: GNU Affero General Public License v3
Classifier: Development Status :: 3 - Alpha
Requires-Python: >=3.10
Requires-Dist: extendable-pydantic >=1.2.0
Requires-Dist: odoo-addon-product-brand <16.1dev,>=16.0dev
Requires-Dist: odoo-addon-shopinvader-base-url <16.1dev,>=16.0dev
Requires-Dist: odoo-addon-shopinvader-product <16.1dev,>=16.0dev
Requires-Dist: odoo-addon-shopinvader-product-seo <16.1dev,>=16.0dev
Requires-Dist: odoo <16.1dev,>=16.0a
